comment_formatter/__init__.py
comment_formatter/formatter.py
comment_formatter/run.py
comment_formatter-0.3.1.dist-info/LICENSE
comment_formatter-0.3.1.dist-info/WHEEL
comment_formatter-0.3.1.dist-info/METADATA
comment_formatter-0.3.1.dist-info/RECORD
